MANIFEST.in
README.md
README.rst
setup.py
flask_restful_swagger_3/__init__.py
flask_restful_swagger_3/constants.py
flask_restful_swagger_3/exceptions.py
flask_restful_swagger_3/swagger.py
flask_restful_swagger_3/swagger_format.py
flask_restful_swagger_3.egg-info/PKG-INFO
flask_restful_swagger_3.egg-info/SOURCES.txt
flask_restful_swagger_3.egg-info/dependency_links.txt
flask_restful_swagger_3.egg-info/not-zip-safe
flask_restful_swagger_3.egg-info/requires.txt
flask_restful_swagger_3.egg-info/top_level.txt
flask_restful_swagger_3/static/LICENSE
flask_restful_swagger_3/static/VERSION
flask_restful_swagger_3/static/favicon-16x16.png
flask_restful_swagger_3/static/favicon-32x32.png
flask_restful_swagger_3/static/oauth2-redirect.html
flask_restful_swagger_3/static/swagger-ui-bundle.js
flask_restful_swagger_3/static/swagger-ui-standalone-preset.js
flask_restful_swagger_3/static/swagger-ui.css
flask_restful_swagger_3/static/swagger-ui.js
flask_restful_swagger_3/templates/index.template.html