Metadata-Version: 1.2
Name: flask-restful-swagger-3
Version: 0.4.6
Summary: Extract swagger specs from your flask-restful project. Project based on flask-restful-swagger-2 by Soeren Wegener.
Home-page: https://gitlab.com/john-ull/framework/flask-restful-swagger-3
Author: Jonathan ULLINDAH
Author-email: jonathan.ullindah@gmail.com
License: MIT
Platform: UNKNOWN
Classifier: Programming Language :: Python :: 3
Classifier: License :: OSI Approved :: MIT License
Classifier: Operating System :: OS Independent
Requires-Python: >=3.6
